simplebot_translator.py
simplebot_translator-1.4.1.dist-info/LICENSE
simplebot_translator-1.4.1.dist-info/METADATA
simplebot_translator-1.4.1.dist-info/WHEEL
simplebot_translator-1.4.1.dist-info/entry_points.txt
simplebot_translator-1.4.1.dist-info/top_level.txt
simplebot_translator-1.4.1.dist-info/RECORD
