Metadata-Version: 2.1
Name: simplebot-translator
Version: 1.4.1
Summary: 🌎 Translator plugin for SimpleBot
Home-page: https://github.com/adbenitez/simplebot_translator
Author: adbenitez
Author-email: adbenitez@nauta.cu
License: MPL
Keywords: simplebot plugin deltachat
Classifier: Development Status :: 4 - Beta
Classifier: Environment :: Plugins
Classifier: Programming Language :: Python :: 3
Classifier: License :: OSI Approved :: Mozilla Public License 2.0 (MPL 2.0)
Classifier: Operating System :: OS Independent
Classifier: Topic :: Utilities
License-File: LICENSE
Requires-Dist: simplebot >=4.0.0
Requires-Dist: translators >=5.4.2
Provides-Extra: dev
Requires-Dist: simplebot >=4.0.0 ; extra == 'dev'
Requires-Dist: translators >=5.4.2 ; extra == 'dev'
Requires-Dist: pytest >=7.1.2 ; extra == 'dev'
Requires-Dist: black >=22.10.0 ; extra == 'dev'
Requires-Dist: mypy >=0.982 ; extra == 'dev'
Requires-Dist: isort >=5.10.1 ; extra == 'dev'
Requires-Dist: pylint >=2.15.3 ; extra == 'dev'
Requires-Dist: pylama >=8.3.8 ; extra == 'dev'
Requires-Dist: types-pkg-resources >=0.1.3 ; extra == 'dev'
Provides-Extra: test
Requires-Dist: pytest >=7.1.2 ; extra == 'test'
